r2sfca/__init__.py
r2sfca/core.py
r2sfca/utils.py
r2sfca-1.1.3.dist-info/licenses/LICENSE
r2sfca-1.1.3.dist-info/METADATA
r2sfca-1.1.3.dist-info/WHEEL
r2sfca-1.1.3.dist-info/top_level.txt
r2sfca-1.1.3.dist-info/RECORD
