Metadata-Version: 2.4
Name: r2sfca
Version: 1.1.3
Summary: Reconciled Two-Step Floating Catchment Area Model for spatial accessibility analysis
Home-page: https://github.com/urbananalytics/r2sfca
Author: Lingbo Liu, Fahui Wang
Author-email: Lingbo Liu <lingboliu@harvard.edu>, Fahui Wang <fwang@lsu.edu>
Maintainer-email: Lingbo Liu <lingboliu@harvard.edu>, Fahui Wang <fwang@lsu.edu>
License: MIT License
Project-URL: Homepage, https://github.com/urbananalytics/r2sfca
Project-URL: Documentation, https://r2sfca.readthedocs.io
Project-URL: Repository, https://github.com/urbananalytics/r2sfca
Project-URL: Issues, https://github.com/urbananalytics/r2sfca/issues
Keywords: spatial analysis,accessibility,2SFCA,i2SFCA,GIS,urban analytics
Classifier: Development Status :: 5 - Production/Stable
Classifier: Intended Audience :: Science/Research
Classifier: License :: OSI Approved :: MIT License
Classifier: Operating System :: OS Independent
Classifier: Programming Language :: Python :: 3
Classifier: Programming Language :: Python :: 3.8
Classifier: Programming Language :: Python :: 3.9
Classifier: Programming Language :: Python :: 3.10
Classifier: Programming Language :: Python :: 3.11
Classifier: Programming Language :: Python :: 3.12
Classifier: Topic :: Scientific/Engineering :: GIS
Classifier: Topic :: Scientific/Engineering :: Information Analysis
Requires-Python: >=3.8
License-File: LICENSE
Requires-Dist: numpy>=1.21.0
Requires-Dist: pandas>=1.3.0
Requires-Dist: scipy>=1.7.0
Requires-Dist: matplotlib>=3.4.0
Requires-Dist: seaborn>=0.11.0
Provides-Extra: dev
Requires-Dist: pytest>=6.0; extra == "dev"
Requires-Dist: pytest-cov>=2.0; extra == "dev"
Requires-Dist: black>=21.0; extra == "dev"
Requires-Dist: flake8>=3.8; extra == "dev"
Requires-Dist: mypy>=0.800; extra == "dev"
Provides-Extra: docs
Requires-Dist: sphinx>=4.0; extra == "docs"
Requires-Dist: sphinx-rtd-theme>=1.0; extra == "docs"
Dynamic: author
Dynamic: home-page
Dynamic: license-file
Dynamic: requires-python
